vistec_ser/__init__.py
vistec_ser/data/__init__.py
vistec_ser/data/ser_dataset.py
vistec_ser/data/ser_slice_dataset.py
vistec_ser/data/datasets/__init__.py
vistec_ser/data/datasets/emodb.py
vistec_ser/data/datasets/thaiser.py
vistec_ser/data/features/__init__.py
vistec_ser/data/features/padding.py
vistec_ser/data/features/transform.py
vistec_ser/evaluation/__init__.py
vistec_ser/evaluation/evaluate.py
vistec_ser/examples/__init__.py
vistec_ser/examples/evaluate_emodb.py
vistec_ser/examples/server.py
vistec_ser/examples/train_aisser.py
vistec_ser/examples/train_fold_aisser.py
vistec_ser/inference/__init__.py
vistec_ser/inference/inference.py
vistec_ser/models/__init__.py
vistec_ser/models/base_model.py
vistec_ser/models/network.py
vistec_ser/models/layers/__init__.py
vistec_ser/models/layers/rnn.py
vistec_ser/utils/__init__.py
vistec_ser/utils/utils.py
vistec_ser-0.4.6a3.dist-info/LICENSE
vistec_ser-0.4.6a3.dist-info/METADATA
vistec_ser-0.4.6a3.dist-info/WHEEL
vistec_ser-0.4.6a3.dist-info/top_level.txt
vistec_ser-0.4.6a3.dist-info/RECORD
