Metadata-Version: 2.1
Name: vistec-ser
Version: 0.4.6a3
Summary: Speech Emotion Recognition models and training using PyTorch
Home-page: https://github.com/tann9949/vistec-ser
Author: Chompakorn Chaksangchaichot
Author-email: chompakorn.cc@gmail.com
License: UNKNOWN
Platform: UNKNOWN
Classifier: Development Status :: 3 - Alpha
Classifier: Intended Audience :: Developers
Classifier: License :: OSI Approved :: Apache Software License
Classifier: Topic :: Software Development :: Libraries :: Python Modules
Classifier: Programming Language :: Python :: 3.6
Requires-Python: >=3.6
Requires-Dist: chardet (<4.0,>=2.0)
Requires-Dist: torch (>=1.7.1)
Requires-Dist: torchvision (>=0.8.2)
Requires-Dist: torchtext (>=0.8.2)
Requires-Dist: torchaudio (>=0.7.2)
Requires-Dist: pytorch-lightning (>=1.2.0)
Requires-Dist: pandas (>=1.1.5)
Requires-Dist: numpy (<1.20.0,>=1.19.2)
Requires-Dist: soundfile (>=0.10.3)
Requires-Dist: PyYAML (!=5.4.*,>=5.1)
Requires-Dist: wget (>=3.2)
Requires-Dist: fastapi (>=0.63.0)
Requires-Dist: aiofiles (>=0.6.0)
Requires-Dist: python-multipart (>=0.0.5)
Requires-Dist: uvicorn (>=0.13.4)
